{
    "meta": {
        "title": "Leaders",
        "description": "Leaders are best for a menu or contents section. To use it, just put a span.leader between the two things you want it to link.",
        "author": "NoTime",
        "date": "13.06.2023"
    },
    "page": [
        {
            "type": "h1",
            "innerHtml": "Leaders"
        },
        {
            "type": "p",
            "innerHtml": "Leaders are best for a menu or contents section. To use it, just put a span.leader between the two things you want it to link."
        },
        {
            "type": "code",
            "innerHtml": "<p class=\"row\">Default <span class=\"leader\"></span> span.leader</p>\n<p class=\"row\">Dashed <span class=\"leader dashed\"></span>pan.leader.dashed</p>\n<p class=\"row\">Solid <span class=\"leader solid\"></span> span.leader.solid</p>\n",
            "language": "html ",
            "sample": true
        },
        {
            "type": "h2",
            "innerHtml": "Structure"
        },
        {
            "type": "code",
            "innerHtml": "<p class=\"row\">Default <span class=\"leader\"></span> span.leader</p>\n",
            "language": "html",
            "sample": false
        },
        {
            "type": "h2",
            "innerHtml": "Options"
        },
        {
            "type": "p",
            "innerHtml": "There are 3 default styles"
        }
    ]
}