{"meta": {"title": "Installation", "description": "a) With cd", "author": "NoTime", "date": "14.06.2023"}, "page": [{"type": "h1", "innerHtml": "Installation"}, {"type": "h2", "innerHtml": "Using CDN"}, {"type": "p", "innerHtml": "a) With cd"}, {"type": "code", "innerHtml": "<!-- BESAMEL-BASE -->\n<link styles TOO:Dod\u011blej!\n\t-- Script >\n<!-- BESAMEL-GENERATED  -->\n", "language": "html", "sample": false}, {"type": "h2", "innerHtml": "Downloading and implementing on your own"}, {"type": "h3", "innerHtml": "a) Compiled"}, {"type": "p", "innerHtml": "TODO: Place link to my github"}, {"type": "h3", "innerHtml": "b) Source code"}, {"type": "p", "innerHtml": "TODO: Place link to my github"}]}